setup.cfg
setup.py
counttrie/__init__.py
counttrie/counttrie.c
counttrie/counttrie.pyx
counttrie/trienode.c
counttrie/trienode.pxd
counttrie/trienode.pyx
counttrie.egg-info/PKG-INFO
counttrie.egg-info/SOURCES.txt
counttrie.egg-info/dependency_links.txt
counttrie.egg-info/requires.txt
counttrie.egg-info/top_level.txt