Metadata-Version: 1.1
Name: counttrie
Version: 0.1.0
Summary: Trie (prefix tree) implementation with some special features for e.g. bioinformatics
Home-page: https://github.com/JoelSjostrand/counttrie
Author: Joel Sjostrand
Author-email: joel.sjostrand@gmail.com
License: Open BSD
Download-URL: https://github.com/JoelSjostrand/counttrie/0.1.0
Keywords: trie,prefix tree,bioinformatics
Platform: UNKNOWN
